HISTORY.md
LICENSE
MANIFEST.in
README.md
flask_request_id.py
setup.py
flask_request_id.egg-info/PKG-INFO
flask_request_id.egg-info/SOURCES.txt
flask_request_id.egg-info/dependency_links.txt
flask_request_id.egg-info/not-zip-safe
flask_request_id.egg-info/requires.txt
flask_request_id.egg-info/top_level.txt