Metadata-Version: 1.1
Name: flask-request-id
Version: 0.1
Summary: Extract yourself some Request IDs.
Home-page: http://github.com/rhyselsmore/flask-request-id
Author: Rhys Elsmore
Author-email: me@rhys.io
License: The ISC License (ISC)
